miaudio/__init__.py
miaudio/core.py
miaudio-0.1.0.dist-info/METADATA
miaudio-0.1.0.dist-info/WHEEL
miaudio-0.1.0.dist-info/top_level.txt
miaudio-0.1.0.dist-info/RECORD
